shipyard_microsoft_excel/__init__.py
shipyard_microsoft_excel/cli/authtest.py
shipyard_microsoft_excel/cli/download.py
shipyard_microsoft_excel/cli/upload.py
shipyard_microsoft_excel/excel_client.py
shipyard_excel-0.1.1.dist-info/METADATA
shipyard_excel-0.1.1.dist-info/WHEEL
shipyard_excel-0.1.1.dist-info/RECORD
