Metadata-Version: 2.1
Name: shipyard-excel
Version: 0.1.1
Summary: A local client for working with Excel files in Microsoft OneDrive
Author: wrp801
Author-email: wespoulsen@gmail.com
Requires-Python: >=3.9,<4.0
Classifier: Programming Language :: Python :: 3
Classifier: Programming Language :: Python :: 3.9
Classifier: Programming Language :: Python :: 3.10
Classifier: Programming Language :: Python :: 3.11
Requires-Dist: msal (>=1.28.1,<2.0.0)
Requires-Dist: openpyxl (>=3.1.4,<4.0.0)
Requires-Dist: pandas (>=2.0,<3.0)
Requires-Dist: requests (==2.31)
Requires-Dist: shipyard-microsoft-onedrive (==0.1.1)
Requires-Dist: shipyard-templates (==0.9.0)
